csh_ldap/__init__.py
csh_ldap/group.py
csh_ldap/member.py
csh_ldap/utility.py
csh_ldap-2.5.3.dist-info/licenses/AUTHORS
csh_ldap-2.5.3.dist-info/licenses/LICENSE
csh_ldap-2.5.3.dist-info/METADATA
csh_ldap-2.5.3.dist-info/WHEEL
csh_ldap-2.5.3.dist-info/pbr.json
csh_ldap-2.5.3.dist-info/top_level.txt
csh_ldap-2.5.3.dist-info/RECORD
