Metadata-Version: 2.4
Name: csh_ldap
Version: 2.5.3
Summary: CSH LDAP ORM
Home-page: https://github.com/ComputerScienceHouse/csh_ldap
Author: Liam Middlebrook
Author-email: liammiddlebrook@gmail.com
License: MIT
Classifier: Natural Language :: English
Classifier: Operating System :: POSIX :: Linux
License-File: LICENSE
License-File: AUTHORS
Requires-Dist: python-ldap==3.4.5
Requires-Dist: srvlookup==3.0.0
Dynamic: author
Dynamic: author-email
Dynamic: classifier
Dynamic: license
Dynamic: license-file
Dynamic: requires-dist
Dynamic: summary
